{
  "project": [
    {
      "name": "Hangman React",
      "id": "1",
      "repo": "https://github.com/zurda/hangman-react",
      "url": "https://zurda.github.io/hangman-react/",
      "type": "frontend"
    },
    {
      "name": "My Storybook",
      "id": "2",
      "repo": "https://github.com/zurda/my-storybook",
      "url": "https://zurda.github.io/my-storybook/",
      "type": "frontend"
    },
    {
      "name": "Portfolio",
      "id": "3",
      "repo": "https://github.com/zurda/portfolio",
      "url": "https://zurda.github.io/portfolio/",
      "type": "frontend"
    },
    {
      "name": "Logbook FE",
      "id": "4",
      "repo": "https://github.com/zurda/coding-logbook",
      "url": "https://zurda.github.io/coding-logbook/",
      "type": "frontend"
    },
    {
      "name": "Logbook BE",
      "id": "5",
      "repo": "https://github.com/zurda/backend-coding-logbook",
      "url": "https://zurda.github.io/coding-logbook/",
      "type": "backend"
    }
  ]
}